freshtomatoes/__init__.py
freshtomatoes-0.3.dist-info/LICENCE.txt
freshtomatoes-0.3.dist-info/METADATA
freshtomatoes-0.3.dist-info/WHEEL
freshtomatoes-0.3.dist-info/top_level.txt
freshtomatoes-0.3.dist-info/RECORD
