Metadata-Version: 2.1
Name: freshtomatoes
Version: 0.3
Summary: freshtomatoes will provide rottentomatoes scores of a given movie
Home-page: UNKNOWN
Author: Sourav Das
Author-email: sourav292922@gmail.com
License: UNKNOWN
Platform: UNKNOWN
Classifier: Programming Language :: Python :: 3
Classifier: License :: OSI Approved :: MIT License
Classifier: Operating System :: OS Independent
